{"url":"https:\/\/cm88995.tw1.ru\/rest\/crm.contact.get.json","info":{"url":"https:\/\/cm88995.tw1.ru\/rest\/crm.contact.get.json","content_type":"application\/json; charset=utf-8","http_code":200,"header_size":602,"request_size":183,"filetime":-1,"ssl_verify_result":0,"redirect_count":0,"total_time":0.794495,"namelookup_time":0.000923,"connect_time":0.00101,"pretransfer_time":0.063183,"size_upload":80,"size_download":2049,"speed_download":2578,"speed_upload":100,"download_content_length":2049,"upload_content_length":80,"starttransfer_time":0.063185,"redirect_time":0,"redirect_url":"","primary_ip":"2a03:6f00:6:1::bce1:1797","certinfo":[],"primary_port":443,"local_ip":"2a03:6f00:6:1::bce1:1797","local_port":35628,"http_version":3,"protocol":2,"ssl_verifyresult":0,"scheme":"HTTPS","appconnect_time_us":63064,"connect_time_us":1010,"namelookup_time_us":923,"pretransfer_time_us":63183,"redirect_time_us":0,"starttransfer_time_us":63185,"total_time_us":794495,"effective_method":"POST"},"params":{"method":"crm.contact.get","params":{"ID":"2","auth":"df65d068007c4d9a007c49a2000000010000079328a4fce4a4b1a33c5e0345722afa92"}},"result":{"result":{"ID":"2","POST":"\u0420\u0443\u043a\u043e\u0432\u043e\u0434\u0438\u0442\u0435\u043b\u044c \u043f\u0440\u043e\u0435\u043a\u0442\u043e\u0432","COMMENTS":"","HONORIFIC":null,"NAME":"\u0411\u043e\u0440\u0438\u0441","SECOND_NAME":"\u0412\u0438\u043a\u0442\u043e\u0440\u043e\u0432\u0438\u0447","LAST_NAME":"\u0421\u043e\u043a\u043e\u043b\u043e\u0432","PHOTO":{"id":112,"showUrl":"\/bitrix\/components\/bitrix\/crm.contact.show\/show_file.php?ownerId=2\u0026fieldName=PHOTO\u0026dynamic=N\u0026fileId=112","downloadUrl":"\/bitrix\/components\/bitrix\/crm.contact.show\/show_file.php?auth=df65d068007c4d9a007c49a2000000010000079328a4fce4a4b1a33c5e0345722afa92\u0026ownerId=2\u0026fieldName=PHOTO\u0026dynamic=N\u0026fileId=112"},"LEAD_ID":null,"TYPE_ID":"SUPPLIER","SOURCE_ID":"TRADE_SHOW","SOURCE_DESCRIPTION":null,"COMPANY_ID":"5","BIRTHDATE":"","EXPORT":"Y","HAS_PHONE":"Y","HAS_EMAIL":"Y","HAS_IMOL":"N","DATE_CREATE":"2025-06-12T06:57:22+03:00","DATE_MODIFY":"2025-09-21T23:30:48+03:00","ASSIGNED_BY_ID":"1","CREATED_BY_ID":"1","MODIFY_BY_ID":"1","OPENED":"Y","ORIGINATOR_ID":null,"ORIGIN_ID":null,"ORIGIN_VERSION":null,"FACE_ID":null,"LAST_ACTIVITY_TIME":"2025-06-12T06:57:22+03:00","ADDRESS":null,"ADDRESS_2":null,"ADDRESS_CITY":null,"ADDRESS_POSTAL_CODE":null,"ADDRESS_REGION":null,"ADDRESS_PROVINCE":null,"ADDRESS_COUNTRY":null,"ADDRESS_LOC_ADDR_ID":null,"UTM_SOURCE":null,"UTM_MEDIUM":null,"UTM_CAMPAIGN":null,"UTM_CONTENT":null,"UTM_TERM":null,"LAST_ACTIVITY_BY":"1","UF_CRM_1758367071504":"2025-09-18T03:00:00+03:00","EMAIL":[{"ID":"8","VALUE_TYPE":"WORK","VALUE":"boris@newtech.net","TYPE_ID":"EMAIL"}],"PHONE":[{"ID":"9","VALUE_TYPE":"MOBILE","VALUE":"8 903 236 55 44","TYPE_ID":"PHONE"}],"WEB":[{"ID":"10","VALUE_TYPE":"WORK","VALUE":"www.newtech.net","TYPE_ID":"WEB"},{"ID":"11","VALUE_TYPE":"FACEBOOK","VALUE":"newtech","TYPE_ID":"WEB"},{"ID":"12","VALUE_TYPE":"TWITTER","VALUE":"net_newtech","TYPE_ID":"WEB"}],"IM":[{"ID":"13","VALUE_TYPE":"SKYPE","VALUE":"boris_power","TYPE_ID":"IM"}]},"time":{"start":1758487067.188299,"finish":1758487067.647252,"duration":0.4589531421661377,"processing":0.11706995964050293,"date_start":"2025-09-21T23:37:47+03:00","date_finish":"2025-09-21T23:37:47+03:00"}}}